djangorescue/__init__.py
djangorescue/middleware.py
djangorescue-0.0.4.dist-info/LICENSE
djangorescue-0.0.4.dist-info/METADATA
djangorescue-0.0.4.dist-info/WHEEL
djangorescue-0.0.4.dist-info/top_level.txt
djangorescue-0.0.4.dist-info/RECORD
