Metadata-Version: 2.1
Name: djangorescue
Version: 0.0.4
Summary: Package to let you serve static and media files via Django pipeline with DEBUG = False.
Home-page: https://github.com/ignusin/djangorescue
Author: Iakov Gnusin
Author-email: y.gnusin@gmail.com
License: UNKNOWN
Platform: UNKNOWN
Classifier: Framework :: Django
Classifier: Environment :: Web Environment
Classifier: Programming Language :: Python :: 3
Classifier: License :: OSI Approved :: MIT License
Classifier: Operating System :: OS Independent
